pytimers/__init__.py
pytimers/clock.py
pytimers/exceptions.py
pytimers/immutable_stack.py
pytimers/py.typed
pytimers/timer.py
pytimers/triggers/__init__.py
pytimers/triggers/base_trigger.py
pytimers/triggers/dummy_trigger.py
pytimers/triggers/logger_trigger.py
pytimers-3.1.dist-info/LICENSE
pytimers-3.1.dist-info/METADATA
pytimers-3.1.dist-info/WHEEL
pytimers-3.1.dist-info/top_level.txt
pytimers-3.1.dist-info/RECORD
