Metadata-Version: 2.1
Name: pytimers
Version: 3.1
Summary: Measuring time to run functions, methods or blocks of code made easy.
Home-page: https://github.com/michalfilippi/pytimers
Author: Michal Filippi
Author-email: michal.filippi@gmail.com
License: UNKNOWN
Platform: UNKNOWN
Classifier: Programming Language :: Python :: 3
Classifier: License :: OSI Approved :: MIT License
Classifier: Operating System :: OS Independent
Requires-Python: >=3.7
Requires-Dist: decorator (>=4.0.0)
